nseconnect/__init__.py
nseconnect/bases.py
nseconnect/cleaners.py
nseconnect/datemgr.py
nseconnect/downloader.py
nseconnect/errors.py
nseconnect/nse.py
nseconnect/ua.py
nseconnect/urls.py
nseconnect/utils.py
nseconnect-1.0.2.dist-info/licenses/LICENSE
nseconnect-1.0.2.dist-info/METADATA
nseconnect-1.0.2.dist-info/WHEEL
nseconnect-1.0.2.dist-info/top_level.txt
nseconnect-1.0.2.dist-info/RECORD
