Metadata-Version: 2.4
Name: nseconnect
Version: 1.0.2
Summary: Python library for extracting real-time data from National Stock Exchange (India)
Home-page: http://github.com/coder1598/nseconnect
Author: Noufal Nazar
Author-email: Noufal Nazar <naufalnazar@icloud.com>
License: MIT
Project-URL: Homepage, http://github.com/coder1598/nseconnect
Keywords: nse,quote,market,stock,equity,india
Classifier: Development Status :: 5 - Production/Stable
Classifier: License :: OSI Approved :: MIT License
Classifier: Programming Language :: Python :: 3 :: Only
Requires-Python: >=3.6
License-File: LICENSE
Requires-Dist: six
Requires-Dist: dateutils
Requires-Dist: requests
Dynamic: author
Dynamic: home-page
Dynamic: license-file
